bj.py
evt_blackjack-0.1.1.dist-info/METADATA
evt_blackjack-0.1.1.dist-info/WHEEL
evt_blackjack-0.1.1.dist-info/entry_points.txt
evt_blackjack-0.1.1.dist-info/top_level.txt
evt_blackjack-0.1.1.dist-info/RECORD
