Metadata-Version: 2.4
Name: evt-blackjack
Version: 0.1.1
Summary: A terminal-based Blackjack trainer
Author: Ethan Votran
Classifier: Programming Language :: Python :: 3
Classifier: Environment :: Console
Classifier: License :: OSI Approved :: MIT License
Requires-Python: >=3.6
Dynamic: author
Dynamic: classifier
Dynamic: description
Dynamic: description-content-type
Dynamic: requires-python
Dynamic: summary
